.DS_Store
sqlvis/__init__.py
sqlvis/atelier-forest.light.css
sqlvis/styles.css.html
sqlvis/vis.py
sqlvis/visualize.js
sqlvis-0.1.0.dist-info/LICENSE
sqlvis-0.1.0.dist-info/METADATA
sqlvis-0.1.0.dist-info/WHEEL
sqlvis-0.1.0.dist-info/top_level.txt
sqlvis-0.1.0.dist-info/RECORD
