Metadata-Version: 2.1
Name: sqlvis
Version: 0.1.0
Summary: A package to represent SQL queries as graphs.
Home-page: https://github.com/Giraphne/sqlvis
Author: Daphne Miedema
Author-email: daphnemiedema@hotmail.com
Classifier: Programming Language :: Python :: 3
Classifier: License :: OSI Approved :: MIT License
Classifier: Operating System :: OS Independent
Classifier: Development Status :: 3 - Alpha
Requires-Python: >=3.6
License-File: LICENSE
